setup.py
src/netaddress/__init__.py
src/netaddress/netaddress.py
src/netaddress/notQuiteURI.py
src/netaddress/pyParseExtensions.py
src/netaddress/rfc3986.py
src/netaddress.egg-info/PKG-INFO
src/netaddress.egg-info/SOURCES.txt
src/netaddress.egg-info/dependency_links.txt
src/netaddress.egg-info/not-zip-safe
src/netaddress.egg-info/requires.txt
src/netaddress.egg-info/top_level.txt
