Metadata-Version: 1.0
Name: netaddress
Version: 0.2.1
Summary: Validating parser for URI's (RFC 3986)
Home-page: http://www.kraeutler.net/vincent/pub/netaddress
Author: Vincent Kraeutler
Author-email: vincent@kraeutler.net
License: BSD License
Platform: UNKNOWN
